CHANGELOG.md
LICENSE.txt
NOTICE.txt
README.md
queasars/__init__.py
queasars/circuit_evaluation/__init__.py
queasars/circuit_evaluation/bitstring_evaluation.py
queasars/circuit_evaluation/circuit_evaluation.py
queasars/circuit_evaluation/configured_primitives.py
queasars/circuit_evaluation/expectation_calculation.py
queasars/circuit_evaluation/mutex_primitives.py
queasars/circuit_evaluation/transpiling_primitives.py
queasars/job_shop_scheduling/__init__.py
queasars/job_shop_scheduling/domain_wall_hamiltonian_encoder.py
queasars/job_shop_scheduling/problem_instances.py
queasars/job_shop_scheduling/random_problem_instances.py
queasars/job_shop_scheduling/scip_solver.py
queasars/job_shop_scheduling/serialization.py
queasars/job_shop_scheduling/visualization.py
queasars/minimum_eigensolvers/__init__.py
queasars/minimum_eigensolvers/base/__init__.py
queasars/minimum_eigensolvers/base/evolutionary_algorithm.py
queasars/minimum_eigensolvers/base/evolving_ansatz_minimum_eigensolver.py
queasars/minimum_eigensolvers/base/evolving_ansatz_minimum_eigensolver_result.py
queasars/minimum_eigensolvers/base/serialization.py
queasars/minimum_eigensolvers/base/termination_criteria.py
queasars/minimum_eigensolvers/evqe/__init__.py
queasars/minimum_eigensolvers/evqe/evolutionary_algorithm/__init__.py
queasars/minimum_eigensolvers/evqe/evolutionary_algorithm/individual.py
queasars/minimum_eigensolvers/evqe/evolutionary_algorithm/mutation.py
queasars/minimum_eigensolvers/evqe/evolutionary_algorithm/population.py
queasars/minimum_eigensolvers/evqe/evolutionary_algorithm/selection.py
queasars/minimum_eigensolvers/evqe/evolutionary_algorithm/speciation.py
queasars/minimum_eigensolvers/evqe/evqe.py
queasars/minimum_eigensolvers/evqe/quantum_circuit/__init__.py
queasars/minimum_eigensolvers/evqe/quantum_circuit/circuit_layer.py
queasars/minimum_eigensolvers/evqe/quantum_circuit/quantum_gate.py
queasars/minimum_eigensolvers/evqe/quantum_circuit/serialization.py
queasars-0.3.1.dist-info/LICENSE.txt
queasars-0.3.1.dist-info/METADATA
queasars-0.3.1.dist-info/WHEEL
queasars-0.3.1.dist-info/RECORD
