Metadata-Version: 2.1
Name: queasars
Version: 0.3.1
Summary: QUEASARS is an open-source, qiskit-based, python package implementing quantum variational eigensolvers which use evolutionary algorithms to find a good ansatz during the optimization process.
License: Apache-2.0
Author: Sven Prüfer
Author-email: sven.pruefer@dlr.de
Requires-Python: >=3.9.0,<3.13
Classifier: License :: OSI Approved :: Apache Software License
Classifier: Operating System :: OS Independent
Classifier: Programming Language :: Python :: 3
Classifier: Programming Language :: Python :: 3.9
Classifier: Programming Language :: Python :: 3.10
Classifier: Programming Language :: Python :: 3.11
Classifier: Programming Language :: Python :: 3.12
Provides-Extra: pyscipopt
Requires-Dist: dask (>=2023.12.0)
Requires-Dist: distributed (>=2023.12.0)
Requires-Dist: numpy (>=1.26)
Requires-Dist: pyscipopt (==4.*) ; extra == "pyscipopt"
Requires-Dist: qiskit (>=1.0.0)
Requires-Dist: qiskit-algorithms (>=0.2.0)
Requires-Dist: qiskit-ibm-runtime (>=0.19.0)
Requires-Dist: qiskit-optimization (>=0.6.0)
Requires-Dist: typing-extensions (>=4.9.0)
